dnntime/__init__.py
dnntime/__version__.py
dnntime/run.py
dnntime/blocks/__init__.py
dnntime/blocks/base.py
dnntime/blocks/eda.py
dnntime/blocks/etl.py
dnntime/blocks/model.py
dnntime/models/__init__.py
dnntime/models/convlstm.py
dnntime/models/gru.py
dnntime/models/lstm.py
dnntime/models/rnn.py
dnntime/tests/__init__.py
dnntime/tests/config_test.py
dnntime/tests/eda_test.py
dnntime/tests/etl_test.py
dnntime/tests/model_test.py
dnntime/utils/__init__.py
dnntime/utils/eda_gen.py
dnntime/utils/eda_stat.py
dnntime/utils/etl_ext.py
dnntime/utils/etl_trans.py
dnntime/utils/metrics.py
dnntime/utils/ts.py
dnntime-0.4.1.dist-info/LICENSE
dnntime-0.4.1.dist-info/METADATA
dnntime-0.4.1.dist-info/WHEEL
dnntime-0.4.1.dist-info/top_level.txt
dnntime-0.4.1.dist-info/RECORD
